easyui/__init__.py
easyui/components.py
easyui/form.py
easyui/layout.py
easyui/py.typed
easyui/threading.py
easyui/window.py
easyui/themes/__init__.py
easyui/themes/default_themes.py
easyui/themes/theme_loader.py
easyui_lib-0.3.1.dist-info/licenses/LICENSE
easyui_lib-0.3.1.dist-info/METADATA
easyui_lib-0.3.1.dist-info/WHEEL
easyui_lib-0.3.1.dist-info/top_level.txt
easyui_lib-0.3.1.dist-info/RECORD
