Metadata-Version: 2.4
Name: easyui-lib
Version: 0.3.1
Summary: Una librería para crear interfaces de usuario de manera sencilla
Author-email: Martin Alejandro Oviedo <martinoviedo.ok@gmail.com>
License-Expression: MIT
Project-URL: Homepage, https://github.com/MartinAlejandroOviedo/EasyUI
Project-URL: Repository, https://github.com/MartinAlejandroOviedo/EasyUI
Project-URL: Issues, https://github.com/MartinAlejandroOviedo/EasyUI/issues
Classifier: Programming Language :: Python :: 3
Classifier: Programming Language :: Python :: 3 :: Only
Classifier: Programming Language :: Python :: 3.8
Classifier: Programming Language :: Python :: 3.9
Classifier: Programming Language :: Python :: 3.10
Classifier: Programming Language :: Python :: 3.11
Classifier: Programming Language :: Python :: 3.12
Classifier: Operating System :: OS Independent
Requires-Python: >=3.8
License-File: LICENSE
Requires-Dist: Pillow>=9.0.0
Requires-Dist: numpy>=1.20.0
Requires-Dist: qtawesome>=1.0.0
Requires-Dist: tinycss2>=1.2.0
Requires-Dist: cssutils>=2.3.0
Requires-Dist: pyyaml>=6.0
Requires-Dist: babel>=2.9.0
Requires-Dist: importlib-resources>=5.0.0
Provides-Extra: dev
Requires-Dist: pytest>=6.0.0; extra == "dev"
Requires-Dist: pytest-qt>=4.0.0; extra == "dev"
Requires-Dist: black>=21.0; extra == "dev"
Requires-Dist: isort>=5.0.0; extra == "dev"
Requires-Dist: mypy>=0.910; extra == "dev"
Provides-Extra: docs
Requires-Dist: sphinx>=4.0.0; extra == "docs"
Requires-Dist: sphinx-rtd-theme>=0.5.0; extra == "docs"
Requires-Dist: sphinx-copybutton>=0.4.0; extra == "docs"
Provides-Extra: sass
Requires-Dist: libsass>=0.21.0; extra == "sass"
Provides-Extra: less
Requires-Dist: lesscpy>=0.15.0; extra == "less"
Provides-Extra: postcss
Requires-Dist: postcss>=8.4.0; extra == "postcss"
Requires-Dist: autoprefixer>=10.4.0; extra == "postcss"
Provides-Extra: tables
Requires-Dist: pandastable>=0.13.0; extra == "tables"
Requires-Dist: tkintertable>=1.0.0; extra == "tables"
Dynamic: license-file
